Topsis_102103409_Bhavya/__init__.py
Topsis_102103409_Bhavya/__main__.py
Topsis_102103409_Bhavya-1.1.3.dist-info/LICENSE
Topsis_102103409_Bhavya-1.1.3.dist-info/METADATA
Topsis_102103409_Bhavya-1.1.3.dist-info/WHEEL
Topsis_102103409_Bhavya-1.1.3.dist-info/top_level.txt
Topsis_102103409_Bhavya-1.1.3.dist-info/RECORD
