Metadata-Version: 2.1
Name: Topsis-102103409-Bhavya
Version: 1.1.3
Summary: This package helps to get the topsis score from the given dataframe
Home-page: UNKNOWN
Author: Bhavya Rampal
Author-email: bhavya3728@gmail.com
License: MIT
Keywords: Topsis,Ranking
Platform: UNKNOWN
Classifier: Development Status :: 3 - Alpha
Classifier: Intended Audience :: Developers
Classifier: Topic :: Software Development :: Build Tools
Classifier: License :: OSI Approved :: MIT License
Classifier: Programming Language :: Python :: 3
Classifier: Programming Language :: Python :: 3.4
Classifier: Programming Language :: Python :: 3.5
Classifier: Programming Language :: Python :: 3.6
License-File: LICENSE
Requires-Dist: pandas
Requires-Dist: numpy
